Nika/__init__.py
Nika/colorprint.py
Nika/config.py
Nika/consumer.py
Nika/error.py
Nika/filter.py
Nika/logger.py
Nika/nika.py
Nika/postgres.py
Nika/producer.py
Nika/response.py
Nika/util.py
Nika-1.1.2.dist-info/LICENSE
Nika-1.1.2.dist-info/METADATA
Nika-1.1.2.dist-info/WHEEL
Nika-1.1.2.dist-info/top_level.txt
Nika-1.1.2.dist-info/RECORD
