Metadata-Version: 2.1
Name: Nika
Version: 1.1.2
Summary: Package for process data from some source
Home-page: https://github.com/bekkazy-k/Nika
Author: Bekkazy Kubanychbekov
Author-email: bekkazy.k@gmail.com
License: UNKNOWN
Platform: UNKNOWN
Classifier: Programming Language :: Python :: 3.7
Classifier: License :: OSI Approved :: MIT License
Classifier: Operating System :: OS Independent
Requires-Python: >=3.7
Requires-Dist: kafka-python (==1.4.6)
Requires-Dist: profig (==0.4.1)
Requires-Dist: psycopg2 (==2.8.2)
